odoo/addons/l10n_br_account/README.rst
odoo/addons/l10n_br_account/__init__.py
odoo/addons/l10n_br_account/__manifest__.py
odoo/addons/l10n_br_account/hooks.py
odoo/addons/l10n_br_account/data/account_tax_group.xml
odoo/addons/l10n_br_account/data/account_tax_template.xml
odoo/addons/l10n_br_account/demo/res_users_demo.xml
odoo/addons/l10n_br_account/i18n/l10n_br_account.pot
odoo/addons/l10n_br_account/i18n/pt_BR.po
odoo/addons/l10n_br_account/images/l10n_br-hover.png
odoo/addons/l10n_br_account/images/l10n_br.png
odoo/addons/l10n_br_account/migrations/14.0.1.0.0/post-migration.py
odoo/addons/l10n_br_account/migrations/14.0.9.0.0/post-migration.py
odoo/addons/l10n_br_account/models/__init__.py
odoo/addons/l10n_br_account/models/account_chart_template.py
odoo/addons/l10n_br_account/models/account_incoterms.py
odoo/addons/l10n_br_account/models/account_journal.py
odoo/addons/l10n_br_account/models/account_move.py
odoo/addons/l10n_br_account/models/account_move_line.py
odoo/addons/l10n_br_account/models/account_tax.py
odoo/addons/l10n_br_account/models/account_tax_group.py
odoo/addons/l10n_br_account/models/account_tax_template.py
odoo/addons/l10n_br_account/models/document.py
odoo/addons/l10n_br_account/models/document_line.py
odoo/addons/l10n_br_account/models/fiscal_decorator_mixin.py
odoo/addons/l10n_br_account/models/fiscal_operation.py
odoo/addons/l10n_br_account/models/fiscal_operation_line.py
odoo/addons/l10n_br_account/models/fiscal_tax.py
odoo/addons/l10n_br_account/models/fiscal_tax_group.py
odoo/addons/l10n_br_account/models/ir_model_data.py
odoo/addons/l10n_br_account/readme/CONFIGURE.rst
odoo/addons/l10n_br_account/readme/CONTRIBUTORS.rst
odoo/addons/l10n_br_account/readme/DESCRIPTION.rst
odoo/addons/l10n_br_account/readme/HISTORY.rst
odoo/addons/l10n_br_account/readme/INSTALL.rst
odoo/addons/l10n_br_account/readme/ROADMAP.rst
odoo/addons/l10n_br_account/readme/USAGE.rst
odoo/addons/l10n_br_account/report/__init__.py
odoo14_addon_l10n_br_account-14.0.15.0.0.dist-info/METADATA
odoo14_addon_l10n_br_account-14.0.15.0.0.dist-info/WHEEL
odoo14_addon_l10n_br_account-14.0.15.0.0.dist-info/top_level.txt
odoo14_addon_l10n_br_account-14.0.15.0.0.dist-info/RECORD
